edc_vitals/__init__.py
edc_vitals/apps.py
edc_vitals/calculators/__init__.py
edc_vitals/calculators/bmi.py
edc_vitals/form_validators/__init__.py
edc_vitals/form_validators/blood_pressure_form_validator_mixin.py
edc_vitals/form_validators/bmi_form_validator_mixin.py
edc_vitals/form_validators/weight_height_with_bmi_form_validator_mixin.py
edc_vitals/migrations/__init__.py
edc_vitals/model_mixins/__init__.py
edc_vitals/model_mixins/blood_pressure_model_mixin.py
edc_vitals/model_mixins/weight_height_bmi_model_mixin.py
edc_vitals/models/__init__.py
edc_vitals/models/fields/__init__.py
edc_vitals/models/fields/blood_pressure.py
edc_vitals/models/fields/heart_rate.py
edc_vitals/models/fields/height.py
edc_vitals/models/fields/respiratory_rate.py
edc_vitals/models/fields/temperature.py
edc_vitals/models/fields/waist_circumference.py
edc_vitals/models/fields/weight.py
edc_vitals/tests/__init__.py
edc_vitals/tests/etc/django_crypto_fields
edc_vitals/tests/etc/user-aes-local.key
edc_vitals/tests/etc/user-aes-restricted.key
edc_vitals/tests/etc/user-rsa-local-private.pem
edc_vitals/tests/etc/user-rsa-local-public.pem
edc_vitals/tests/etc/user-rsa-restricted-private.pem
edc_vitals/tests/etc/user-rsa-restricted-public.pem
edc_vitals/tests/etc/user-salt-local.key
edc_vitals/tests/etc/user-salt-restricted.key
edc_vitals/tests/models.py
edc_vitals/tests/tests/__init__.py
edc_vitals/tests/tests/test_blood_pressure.py
edc_vitals/tests/tests/test_calculators.py
edc_vitals/tests/tests/test_heart_rate.py
edc_vitals/tests/tests/test_respiratory_rate.py
edc_vitals/tests/tests/test_temperature.py
edc_vitals/tests/tests/test_weight_height_bmi.py
edc_vitals/tests/urls.py
edc_vitals/utils.py
edc_vitals/validators.py
edc_vitals-1.1.3.dist-info/licenses/LICENSE
edc_vitals-1.1.3.dist-info/WHEEL
edc_vitals-1.1.3.dist-info/METADATA
edc_vitals-1.1.3.dist-info/RECORD
